{
    "sourceFile": "Chapter 1/1.9.cpp",
    "activeCommit": 0,
    "commits": [
        {
            "activePatchIndex": 4,
            "patches": [
                {
                    "date": 1636514704491,
                    "content": "Index: \n===================================================================\n--- \n+++ \n"
                },
                {
                    "date": 1636514728679,
                    "content": "Index: \n===================================================================\n--- \n+++ \n@@ -1,3 +1,9 @@\n #include <iostream>\r\n int main()\r\n-{}\n\\ No newline at end of file\n+{\r\n+    int var=50,sum;\r\n+    while(var<=100)\r\n+    {\r\n+        \r\n+    }\r\n+}\n\\ No newline at end of file\n"
                },
                {
                    "date": 1636514744605,
                    "content": "Index: \n===================================================================\n--- \n+++ \n@@ -3,7 +3,9 @@\n {\r\n     int var=50,sum;\r\n     while(var<=100)\r\n     {\r\n-        \r\n+        sum+=var;\r\n+        var++;\r\n     }\r\n+    cout<<\r\n }\n\\ No newline at end of file\n"
                },
                {
                    "date": 1636514765576,
                    "content": "Index: \n===================================================================\n--- \n+++ \n@@ -6,6 +6,6 @@\n     {\r\n         sum+=var;\r\n         var++;\r\n     }\r\n-    cout<<\r\n+    std::cout<<\"The sum from 50 to 100 is\"<<sum<<endl;\r\n }\n\\ No newline at end of file\n"
                },
                {
                    "date": 1636514773328,
                    "content": "Index: \n===================================================================\n--- \n+++ \n@@ -1,11 +1,12 @@\n #include <iostream>\r\n int main()\r\n {\r\n-    int var=50,sum;\r\n-    while(var<=100)\r\n+    int var = 50, sum;\r\n+    while (var <= 100)\r\n     {\r\n-        sum+=var;\r\n+        sum += var;\r\n         var++;\r\n     }\r\n-    std::cout<<\"The sum from 50 to 100 is\"<<sum<<endl;\r\n+    std::cout << \"The sum from 50 to 100 is\" << sum << endl;\r\n+    return 0;\r\n }\n\\ No newline at end of file\n"
                }
            ],
            "date": 1636514704491,
            "name": "Commit-0",
            "content": "#include <iostream>\r\nint main()\r\n{}"
        }
    ]
}